ltd_rust-0.1.6.dist-info/METADATA
ltd_rust-0.1.6.dist-info/WHEEL
ltd_rust-0.1.6.dist-info/license_files/LICENSE.txt
ltd_rust/ltd_rust.pyi
ltd_rust/py.typed
ltd_rust/__init__.py
ltd_rust/ltd_rust.cp38-win_amd64.pyd
ltd_rust-0.1.6.dist-info/RECORD
